{"data":{"isSZX":0,"level":3,"provCode":"13","provName":"河北省","cityCode":"131003","cityName":"广阳区","childs":[{"code":"131003001","name":"银河北路街道","level":4},{"code":"131003002","name":"爱民东道街道","level":4},{"code":"131003003","name":"解放道街道","level":4},{"code":"131003004","name":"新开路街道","level":4},{"code":"131003005","name":"新源道街道","level":4},{"code":"131003100","name":"南尖塔镇","level":4},{"code":"131003101","name":"万庄镇","level":4},{"code":"131003102","name":"九州镇","level":4},{"code":"131003200","name":"北旺乡","level":4},{"code":"131003500","name":"新世纪步行街管理委员会","level":4}]}}