{"data":{"isSZX":0,"level":3,"provCode":"14","provName":"山西省","cityCode":"140423","cityName":"襄垣县","childs":[{"code":"140423100","name":"古韩镇","level":4},{"code":"140423101","name":"王桥镇","level":4},{"code":"140423102","name":"侯堡镇","level":4},{"code":"140423103","name":"夏店镇","level":4},{"code":"140423104","name":"虒亭镇","level":4},{"code":"140423105","name":"西营镇","level":4},{"code":"140423106","name":"王村镇","level":4},{"code":"140423107","name":"下良镇","level":4},{"code":"140423200","name":"善福乡","level":4},{"code":"140423201","name":"北底乡","level":4},{"code":"140423202","name":"上马乡","level":4},{"code":"140423400","name":"富阳工业园区","level":4},{"code":"140423401","name":"社区管理服务中心","level":4}]}}