{"data":{"isSZX":0,"level":3,"provCode":"22","provName":"吉林省","cityCode":"222405","cityName":"龙井市","childs":[{"code":"222405001","name":"安民街道","level":4},{"code":"222405002","name":"龙门街道","level":4},{"code":"222405100","name":"开山屯镇","level":4},{"code":"222405102","name":"老头沟镇","level":4},{"code":"222405103","name":"三合镇","level":4},{"code":"222405104","name":"东盛涌镇","level":4},{"code":"222405105","name":"智新镇","level":4},{"code":"222405200","name":"德新乡","level":4},{"code":"222405201","name":"白金乡","level":4},{"code":"222405400","name":"龙井市林业局","level":4},{"code":"222405401","name":"龙井大苏果树农场","level":4}]}}