{"data":{"isSZX":0,"level":3,"provCode":"23","provName":"黑龙江省","cityCode":"231124","cityName":"孙吴县","childs":[{"code":"231124001","name":"孙吴城区街道","level":4},{"code":"231124100","name":"孙吴镇","level":4},{"code":"231124101","name":"辰清镇","level":4},{"code":"231124201","name":"西兴乡","level":4},{"code":"231124202","name":"沿江满族乡","level":4},{"code":"231124203","name":"腰屯乡","level":4},{"code":"231124204","name":"卧牛河乡","level":4},{"code":"231124205","name":"群山乡","level":4},{"code":"231124206","name":"奋斗乡","level":4},{"code":"231124207","name":"红旗乡","level":4},{"code":"231124208","name":"正阳山乡","level":4},{"code":"231124210","name":"清溪乡","level":4},{"code":"231124402","name":"前进林场","level":4},{"code":"231124403","name":"大河口林场","level":4},{"code":"231124404","name":"正阳林场","level":4},{"code":"231124405","name":"平山林场","level":4},{"code":"231124406","name":"沿江林场","level":4},{"code":"231124407","name":"辰清林场","level":4},{"code":"231124408","name":"红旗林场","level":4},{"code":"231124409","name":"向阳林场","level":4},{"code":"231124410","name":"良种场","level":4},{"code":"231124411","name":"种畜场","level":4},{"code":"231124500","name":"红色边疆农场","level":4}]}}