{"data":{"isSZX":0,"level":3,"provCode":"35","provName":"福建省","cityCode":"350781","cityName":"邵武市","childs":[{"code":"350781001","name":"昭阳街道","level":4},{"code":"350781002","name":"通泰街道","level":4},{"code":"350781003","name":"水北街道","level":4},{"code":"350781004","name":"晒口街道","level":4},{"code":"350781100","name":"城郊镇","level":4},{"code":"350781101","name":"水北镇","level":4},{"code":"350781102","name":"下沙镇","level":4},{"code":"350781103","name":"卫闽镇","level":4},{"code":"350781104","name":"沿山镇","level":4},{"code":"350781105","name":"拿口镇","level":4},{"code":"350781106","name":"洪墩镇","level":4},{"code":"350781107","name":"大埠岗镇","level":4},{"code":"350781108","name":"和平镇","level":4},{"code":"350781109","name":"肖家坊镇","level":4},{"code":"350781110","name":"大竹镇","level":4},{"code":"350781111","name":"吴家塘镇","level":4},{"code":"350781200","name":"桂林乡","level":4},{"code":"350781201","name":"张厝乡","level":4},{"code":"350781202","name":"金坑乡","level":4}]}}