{"data":{"isSZX":0,"level":3,"provCode":"44","provName":"广东省","cityCode":"440117","cityName":"从化区","childs":[{"code":"440117001","name":"街口街道","level":4},{"code":"440117002","name":"江埔街道","level":4},{"code":"440117003","name":"城郊街道","level":4},{"code":"440117103","name":"温泉镇","level":4},{"code":"440117104","name":"良口镇","level":4},{"code":"440117107","name":"吕田镇","level":4},{"code":"440117111","name":"太平镇","level":4},{"code":"440117113","name":"鳌头镇","level":4},{"code":"440117402","name":"流溪河林场","level":4},{"code":"440117404","name":"黄龙带水库管理处","level":4},{"code":"440117405","name":"大岭山林场","level":4}]}}