{"data":{"isSZX":0,"level":3,"provCode":"45","provName":"广西壮族自治区","cityCode":"450206","cityName":"柳江区","childs":[{"code":"450206100","name":"拉堡镇","level":4},{"code":"450206101","name":"里雍镇","level":4},{"code":"450206102","name":"百朋镇","level":4},{"code":"450206103","name":"成团镇","level":4},{"code":"450206104","name":"洛满镇","level":4},{"code":"450206105","name":"流山镇","level":4},{"code":"450206106","name":"三都镇","level":4},{"code":"450206107","name":"里高镇","level":4},{"code":"450206108","name":"进德镇","level":4},{"code":"450206109","name":"穿山镇","level":4},{"code":"450206110","name":"土博镇","level":4},{"code":"450206111","name":"白沙镇","level":4},{"code":"450206400","name":"新兴工业园","level":4},{"code":"450206401","name":"新兴农场","level":4}]}}