{"data":{"isSZX":0,"level":3,"provCode":"45","provName":"广西壮族自治区","cityCode":"451226","cityName":"环江毛南族自治县","childs":[{"code":"451226100","name":"思恩镇","level":4},{"code":"451226101","name":"水源镇","level":4},{"code":"451226102","name":"洛阳镇","level":4},{"code":"451226103","name":"川山镇","level":4},{"code":"451226104","name":"明伦镇","level":4},{"code":"451226105","name":"东兴镇","level":4},{"code":"451226200","name":"大才乡","level":4},{"code":"451226202","name":"下南乡","level":4},{"code":"451226204","name":"大安乡","level":4},{"code":"451226205","name":"长美乡","level":4},{"code":"451226206","name":"龙岩乡","level":4},{"code":"451226207","name":"驯乐苗族乡","level":4}]}}