{"data":{"isSZX":0,"level":3,"provCode":"65","provName":"新疆维吾尔自治区","cityCode":"652928","cityName":"阿瓦提县","childs":[{"code":"652928100","name":"阿瓦提镇","level":4},{"code":"652928101","name":"乌鲁却勒镇","level":4},{"code":"652928102","name":"拜什艾日克镇","level":4},{"code":"652928200","name":"阿依巴格乡","level":4},{"code":"652928201","name":"塔木托格拉克乡","level":4},{"code":"652928202","name":"英艾日克乡","level":4},{"code":"652928203","name":"多浪乡","level":4},{"code":"652928204","name":"巴格托格拉克乡","level":4},{"code":"652928405","name":"阿克苏监狱","level":4}]}}